instahashtag/__init__.py
instahashtag/api.py
instahashtag/http.py
instahashtag/utils.py
instahashtag/wrapper/__init__.py
instahashtag/wrapper/graph.py
instahashtag/wrapper/maps.py
instahashtag/wrapper/tag.py
instahashtag-1.0.0.dist-info/AUTHORS
instahashtag-1.0.0.dist-info/LICENSE
instahashtag-1.0.0.dist-info/METADATA
instahashtag-1.0.0.dist-info/WHEEL
instahashtag-1.0.0.dist-info/pbr.json
instahashtag-1.0.0.dist-info/top_level.txt
instahashtag-1.0.0.dist-info/RECORD
