Metadata-Version: 2.1
Name: instahashtag
Version: 1.0.0
Summary: Unofficial Python wrapper for DisplayPurposes.com.
Home-page: https://github.com/synchronizing/instahashtag
Author: Felipe Faria
Author-email: felipefaria@hey.com
License: MIT
Project-URL: Bug Tracker, https://github.com/synchronizing/instahashtag/issues
Project-URL: Documentation, https://github.com/synchronizing/instahashtag/
Project-URL: Source Code, https://github.com/synchronizing/instahashtag/tree/master
Keywords: instagram,displaypurposes,wrapper
Platform: UNKNOWN
Classifier: Programming Language :: Python :: Implementation :: CPython
Classifier: Development Status :: 5 - Production/Stable
Classifier: License :: OSI Approved :: MIT License
Classifier: Natural Language :: English
Classifier: Topic :: Software Development :: Libraries
Classifier: Topic :: Utilities
Requires-Dist: requests
Requires-Dist: aiohttp
